gpx_parser/__init__.py
gpx_parser/geometry/__init__.py
gpx_parser/geometry/point.py
gpx_parser/io/__init__.py
gpx_parser/io/device.py
gpx_parser/io/readable.py
gpx_parser/io/writable.py
gpx_parser/io/file/__init__.py
gpx_parser/io/file/file.py
gpx_parser/io/file/file_is_not_a_file_error.py
gpx_parser/io/file/handle.py
gpx_parser/io/file/invalid_file_persmission_error.py
gpx_parser/parser/__init__.py
gpx_parser/parser/gpx_file_parser.py
gpx_parser/parser/gpx_format_not_supported_error.py
gpx_parser/parser/gpx_parse_error.py
gpx_parser/parser/gpx_track_interval.py
gpx_parser/parser/parser.py
gpx_renderer/__init__.py
gpx_renderer/factory.py
gpx_renderer/line.py
gpx_renderer/renderer.py
gpx_renderer/renderer_not_found_error.py
gpx_renderer/terminal_colors.py
gpx_renderer/vector.py
gpx_renderer/renderers/__init__.py
gpx_renderer/renderers/matplotlib.py
gpx_renderer/renderers/stdout.py
gpx_renderer/renderers/distance/__init__.py
gpx_renderer/renderers/distance/matplotlib.py
gpx_renderer/renderers/distance/stdout.py
gpx_renderer/renderers/time/__init__.py
gpx_renderer/renderers/time/matplotlib.py
gpx_renderer/renderers/time/stdout.py
gpxpr/__init__.py
gpxpr/__version__.py
gpxpr/argparser.py
gpxpr/main.py
gpxpr-0.0.3.dist-info/LICENSE
gpxpr-0.0.3.dist-info/METADATA
gpxpr-0.0.3.dist-info/WHEEL
gpxpr-0.0.3.dist-info/entry_points.txt
gpxpr-0.0.3.dist-info/top_level.txt
gpxpr-0.0.3.dist-info/RECORD
