Metadata-Version: 2.1
Name: gpxpr
Version: 0.0.3
Summary: GPX parser and renderer
Home-page: https://github.com/Kruhlmann/gpxpr
Maintainer: Andreas Krühlmann
Maintainer-email: andreas@kruhlmann.dev
License: UNKNOWN
Platform: UNKNOWN
Requires-Python: >=3.9
License-File: LICENSE
Requires-Dist: typer (==0.3.2)
Requires-Dist: gpxpy
Requires-Dist: matplotlib
Provides-Extra: all
Requires-Dist: isort ; extra == 'all'
Requires-Dist: wemake-python-styleguide ; extra == 'all'
Requires-Dist: mypy ; extra == 'all'
Requires-Dist: black ; extra == 'all'
Requires-Dist: dlint ; extra == 'all'
Requires-Dist: nitpick ; extra == 'all'
Requires-Dist: cohesion ; extra == 'all'
Requires-Dist: pyformat ; extra == 'all'
Requires-Dist: add-trailing-comma ; extra == 'all'
Requires-Dist: pre-commit ; extra == 'all'
Requires-Dist: devtools[pygments] ; extra == 'all'
Requires-Dist: pytest ; extra == 'all'
Requires-Dist: pytest-cov ; extra == 'all'
Requires-Dist: pytest-xdist ; extra == 'all'
Requires-Dist: pytest-mock ; extra == 'all'
Requires-Dist: pytest-asyncio ; extra == 'all'
Provides-Extra: dev
Requires-Dist: isort ; extra == 'dev'
Requires-Dist: wemake-python-styleguide ; extra == 'dev'
Requires-Dist: mypy ; extra == 'dev'
Requires-Dist: black ; extra == 'dev'
Requires-Dist: dlint ; extra == 'dev'
Requires-Dist: nitpick ; extra == 'dev'
Requires-Dist: cohesion ; extra == 'dev'
Requires-Dist: pyformat ; extra == 'dev'
Requires-Dist: add-trailing-comma ; extra == 'dev'
Requires-Dist: pre-commit ; extra == 'dev'
Requires-Dist: devtools[pygments] ; extra == 'dev'
Provides-Extra: tests
Requires-Dist: pytest ; extra == 'tests'
Requires-Dist: pytest-cov ; extra == 'tests'
Requires-Dist: pytest-xdist ; extra == 'tests'
Requires-Dist: pytest-mock ; extra == 'tests'
Requires-Dist: pytest-asyncio ; extra == 'tests'
